{
    "@context": ["dtmi:dtdl:context;2"],
    "@type": "Interface",
    "@id": "dtmi:sdv:vehicle;1",
    "description": "Vehicle Interface.",
    "contents": [
        {
              "@type": "Property",
              "@id": "dtmi:sdv:vehicle:vehicle_rpm;1",
              "name": "vehicle_rpm",
              "description": "Vehicle rpm.",
              "schema": "integer"
        },
        {
              "@type": "Property",
              "@id": "dtmi:sdv:vehicle:vehicle_fuel;1",
              "name": "vehicle_fuel",
              "description": "Vehicle fuel.",
              "schema": "integer"
        },
        {
              "@type": "Property",
              "@id": "dtmi:sdv:vehicle:vehicle_mileage;1",
              "name": "vehicle_mileage",
              "description": "Vehicle mileage.",
              "schema": "integer"
        },
        {
              "@type": "Property",
              "@id": "dtmi:sdv:vehicle:vehicle_gear;1",
              "name": "vehicle_gear",
              "description": "Vehicle gear.",
              "schema": "integer"
        },
        {
              "@type": "Property",
              "@id": "dtmi:sdv:vehicle:vehicle_speed;1",
              "name": "vehicle_speed",
              "description": "Vehicle speed.",
              "schema": "integer"
        },
    ]
}
